SpinExplorer/SpinConverter.py
SpinExplorer/SpinProcess.py
SpinExplorer/SpinView.py
SpinExplorer/__init__.py
spinexplorer-1.3.dist-info/licenses/LICENSE
spinexplorer-1.3.dist-info/METADATA
spinexplorer-1.3.dist-info/WHEEL
spinexplorer-1.3.dist-info/entry_points.txt
spinexplorer-1.3.dist-info/top_level.txt
spinexplorer-1.3.dist-info/RECORD
