Metadata-Version: 2.4
Name: SpinExplorer
Version: 1.3
Summary: A package for NMR processing and analysis
Author: James Eaton, Andrew Baldwin (University of Oxford)
License-Expression: MIT
Project-URL: Homepage, https://github.com/james-eaton-1/SpinExplorer
Project-URL: Issues, https://github.com/james-eaton-1/SpinExplorer/issues
Requires-Python: >3.11
License-File: LICENSE
Requires-Dist: wxPython>=4.2.2
Requires-Dist: numpy==2.3.0
Requires-Dist: matplotlib==3.10.3
Requires-Dist: nmrglue==0.11
Requires-Dist: scipy==1.15.3
Requires-Dist: darkdetect==0.8.0
Dynamic: license-file
